netsuite_async/__init__.py
netsuite_async/catalog.py
netsuite_async/client/__init__.py
netsuite_async/client/accessors.py
netsuite_async/client/oauth.py
netsuite_async/client/params.py
netsuite_async/client/rest.py
netsuite_async/client/rest.pyi
netsuite_async/exceptions.py
netsuite_async/models/records.py
netsuite_async/signature.py
netsuite_async-0.2.4.dist-info/WHEEL
netsuite_async-0.2.4.dist-info/METADATA
netsuite_async-0.2.4.dist-info/RECORD
