Metadata-Version: 2.3
Name: netsuite-async
Version: 0.2.4
Summary: High-performance async Python client for NetSuite REST API with concurrency controls and intelligent pagination
Keywords: netsuite,async,rest,api,client,erp,oauth
Author: Michael Drummond
Author-email: Michael Drummond <97915761+MichaelD3289@users.noreply.github.com>
Classifier: Development Status :: 4 - Beta
Classifier: Intended Audience :: Developers
Classifier: License :: OSI Approved :: MIT License
Classifier: Operating System :: OS Independent
Classifier: Programming Language :: Python :: 3
Classifier: Programming Language :: Python :: 3.12
Classifier: Topic :: Internet :: WWW/HTTP :: HTTP Servers
Classifier: Topic :: Office/Business :: Financial :: Accounting
Classifier: Topic :: Software Development :: Libraries :: Python Modules
Classifier: Typing :: Typed
Requires-Dist: authlib>=1.6.5
Requires-Dist: httpx>=0.28.1
Requires-Dist: pytest>=7.0 ; extra == 'dev'
Requires-Dist: pytest-asyncio>=0.21.0 ; extra == 'dev'
Requires-Dist: pytest-cov>=4.0 ; extra == 'dev'
Requires-Dist: black>=23.0 ; extra == 'dev'
Requires-Dist: ruff>=0.1.0 ; extra == 'dev'
Requires-Dist: mypy>=1.0 ; extra == 'dev'
Requires-Python: >=3.12
Project-URL: Homepage, https://github.com/MichaelD3289/netsuite-async
Project-URL: Repository, https://github.com/MichaelD3289/netsuite-async
Project-URL: Issues, https://github.com/MichaelD3289/netsuite-async/issues
Project-URL: Documentation, https://github.com/MichaelD3289/netsuite-async#readme
Provides-Extra: dev
